hera_matlab/__init__.py
hera_matlab/__init__.pyi
hera_matlab/hera_matlab.ctf
hera_matlab/install_runtime.py
hera_matlab/runtime_wrapper.py
hera_matlab-1.2.1.dist-info/licenses/LICENSE
hera_matlab-1.2.1.dist-info/METADATA
hera_matlab-1.2.1.dist-info/WHEEL
hera_matlab-1.2.1.dist-info/top_level.txt
hera_matlab-1.2.1.dist-info/RECORD
