Metadata-Version: 2.4
Name: hera-matlab
Version: 1.2.1
Summary: A Python interface to hera_matlab
Home-page: https://github.com/lerdmann1601/HERA-Matlab
Author: Lukas von Erdmannsdorff
License: MIT
Project-URL: Bug Tracker, https://github.com/lerdmann1601/HERA-Matlab/issues
Project-URL: Source Code, https://github.com/lerdmann1601/HERA-Matlab
Project-URL: Documentation, https://lerdmann1601.github.io/HERA-Matlab/
Keywords: ranking,benchmarking,statistics,effect-size,bootstrapping,significance-testing,matlab-interface,hierarchical-compensatory,scientific-computing
Platform: Linux
Platform: Windows
Platform: macOS
Classifier: Programming Language :: Python :: 3
Classifier: Programming Language :: Python :: 3.9
Classifier: Programming Language :: Python :: 3.10
Classifier: Programming Language :: Python :: 3.11
Classifier: Programming Language :: Python :: 3.12
Classifier: License :: OSI Approved :: MIT License
Classifier: Operating System :: OS Independent
Classifier: Topic :: Scientific/Engineering
Classifier: Topic :: Scientific/Engineering :: Mathematics
Classifier: Topic :: Scientific/Engineering :: Bio-Informatics
Classifier: Intended Audience :: Science/Research
Classifier: Topic :: Software Development :: Libraries :: Python Modules
Requires-Python: >=3.9, <3.13
License-File: LICENSE
Dynamic: author
Dynamic: classifier
Dynamic: description
Dynamic: description-content-type
Dynamic: home-page
Dynamic: keywords
Dynamic: license
Dynamic: license-file
Dynamic: platform
Dynamic: project-url
Dynamic: requires-python
Dynamic: summary
